LICENSE
MANIFEST.in
README.md
enable_d3_slider.json
requirements.txt
setup.cfg
setup.py
jupyter_widget_d3_slider/__init__.py
jupyter_widget_d3_slider/__meta__.py
jupyter_widget_d3_slider/widget.py
jupyter_widget_d3_slider.egg-info/PKG-INFO
jupyter_widget_d3_slider.egg-info/SOURCES.txt
jupyter_widget_d3_slider.egg-info/dependency_links.txt
jupyter_widget_d3_slider.egg-info/not-zip-safe
jupyter_widget_d3_slider.egg-info/requires.txt
jupyter_widget_d3_slider.egg-info/top_level.txt
jupyter_widget_d3_slider/static/extension.js
jupyter_widget_d3_slider/static/index.js
jupyter_widget_d3_slider/static/index.js.map