Metadata-Version: 1.1
Name: jupyter-widget-d3-slider
Version: 0.1.9
Summary: d3 based slider Jupyter Widget - for demo
Home-page: https://gitlab.com/oscar6echo/jupyter-widget-d3-slider
Author: oscar6echo
Author-email: olivier.borderies@gmail.com
License: UNKNOWN
Keywords: jupyter-widget,d3,slider
Platform: UNKNOWN
Classifier: Development Status :: 4 - Beta
Classifier: License :: OSI Approved :: MIT License
Classifier: Programming Language :: Python :: 3.5
Classifier: Programming Language :: Python :: 3.6
